freqkey/__init__.py
freqkey-0.0.3.dist-info/LICENSE
freqkey-0.0.3.dist-info/METADATA
freqkey-0.0.3.dist-info/WHEEL
freqkey-0.0.3.dist-info/entry_points.txt
freqkey-0.0.3.dist-info/top_level.txt
freqkey-0.0.3.dist-info/RECORD
