Metadata-Version: 2.1
Name: freqkey
Version: 0.0.3
Summary: Counts your keypresses
Home-page: https://github.com/vixus0/freqkey
Author: Anshul Sirur
Author-email: vixus0@gmail.com
License: UNKNOWN
Platform: UNKNOWN
Classifier: Programming Language :: Python :: 3
Classifier: License :: OSI Approved :: MIT License
Classifier: Operating System :: OS Independent
Requires-Dist: inputs
